LICENSE
MANIFEST.in
README.md
setup.cfg
setup.py
tekrar/__init__.py
tekrar/tekrar.py
tekrar.egg-info/PKG-INFO
tekrar.egg-info/SOURCES.txt
tekrar.egg-info/dependency_links.txt
tekrar.egg-info/requires.txt
tekrar.egg-info/top_level.txt