Metadata-Version: 2.1
Name: tekrar
Version: 0.1.1
Summary: create loading animation in python cli project ...
Home-page: https://github.com/sys113/tekrar
Author: SYS113
Author-email: 051.SYS113@gmail.com
License: UNKNOWN
Keywords: tekrar,wait,loading
Platform: UNKNOWN
Classifier: Intended Audience :: Developers
Classifier: License :: OSI Approved :: MIT License
Classifier: Natural Language :: English
Classifier: Operating System :: OS Independent
Classifier: Programming Language :: Python :: Implementation
Classifier: Topic :: Software Development :: Libraries :: Python Modules
